setup.cfg
setup.py
src/pysony.py
src/pysony.egg-info/PKG-INFO
src/pysony.egg-info/SOURCES.txt
src/pysony.egg-info/dependency_links.txt
src/pysony.egg-info/top_level.txt