Metadata-Version: 1.1
Name: pysony
Version: 0.1.9
Summary: Sony Camera Remote API for python
Home-page: https://github.com/Bloodevil/sony_camera_api
Author: Yeaji Shin
Author-email: yeahjishin@gmail.com
License: MIT
Download-URL: https://github.com/Bloodevil/sony_camera_api/tarball/0.1.9
Keywords: sony,camera,remote,api
Platform: UNKNOWN
Classifier: License :: OSI Approved :: MIT License
Classifier: Programming Language :: Python :: 2
